cloud_fits/__init__.py
cloud_fits/bucket_operations.py
cloud_fits/exceptions.py
cloud_fits/local_index.py
cloud_fits/auth/__init__.py
cloud_fits/auth/aws.py
cloud_fits/data_types/__init__.py
cloud_fits/data_types/shortcuts.py
cloud_fits/data_types/utils.py
cloud_fits/fits_index/__init__.py
cloud_fits/fits_index/factory.py
cloud_fits-0.1.1.dist-info/LICENSE
cloud_fits-0.1.1.dist-info/METADATA
cloud_fits-0.1.1.dist-info/WHEEL
cloud_fits-0.1.1.dist-info/entry_points.txt
cloud_fits-0.1.1.dist-info/top_level.txt
cloud_fits-0.1.1.dist-info/RECORD
