Metadata-Version: 2.1
Name: cloud-fits
Version: 0.1.1
Summary: Cloud Optimized Fits
Home-page: https://github.com/jbcurtin/cloud-fits
Author: Joe Curtin <42@jbcurtin.io
Author-email: cloud-fits@jbcurtin.io
License: MIT
Platform: UNKNOWN
Classifier: Operating System :: OS Independent
Classifier: Programming Language :: Python
Classifier: Programming Language :: Python :: 3
Classifier: Programming Language :: Python :: 3.6
Classifier: Programming Language :: Python :: 3.7
Classifier: Programming Language :: Python :: 3.8
Classifier: Programming Language :: Python :: 3 :: Only
Requires-Python: >=3.6
Requires-Dist: requests (==2.23.0)
Requires-Dist: PyYAML (==5.1.2)
Requires-Dist: numpy (==1.18.2)
Requires-Dist: astropy (==4.0.1.post1)
